looplive/__init__.py
looplive/cli.py
looplive/main.py
looplive/controller/__init__.py
looplive/controller/bili_controller.py
looplive/controller/config_controller.py
looplive/controller/ytb_controller.py
looplive/execute/__init__.py
looplive/execute/scan_and_execute.py
looplive/model/__init__.py
looplive/model/model.py
looplive/tests/__init__.py
looplive/tests/test_execute.py
looplive-0.0.2.dist-info/METADATA
looplive-0.0.2.dist-info/WHEEL
looplive-0.0.2.dist-info/entry_points.txt
looplive-0.0.2.dist-info/licenses/LICENSE
looplive-0.0.2.dist-info/RECORD
