Metadata-Version: 2.4
Name: looplive
Version: 0.0.2
Summary: The Python toolkit package and cli designed for auto loop live.
Project-URL: Homepage, https://github.com/timerring/looplive
Author: timerring
License: MIT License
License-File: LICENSE
Classifier: License :: OSI Approved :: MIT License
Classifier: Operating System :: OS Independent
Classifier: Programming Language :: Python :: 3
Requires-Python: >=3.6
